vp_models/__init__.py
vp_models/models/Decision_tree.py
vp_models/models/Knn.py
vp_models/models/Linear_regression.py
vp_models/models/Logistic_regression.py
vp_models/models/Multivariate_regression.py
vp_models/models/Random_forest.py
vp_models/models/__init__.py
vp_models/utils/__init__.py
vp_models/utils/data_processing.py
vp_models/utils/evaluation.py
vp_models-1.0.2.dist-info/METADATA
vp_models-1.0.2.dist-info/WHEEL
vp_models-1.0.2.dist-info/entry_points.txt
vp_models-1.0.2.dist-info/top_level.txt
vp_models-1.0.2.dist-info/RECORD
